{"cameraMode":{"drawMode":0,"name":"Shaded","section":"Shading Mode"},"sceneLighting":false,"audioPlay":false,"sceneViewState":{"m_AlwaysRefresh":false,"showFog":true,"showSkybox":false,"showFlares":true,"showImageEffects":true,"showParticleSystems":true,"showVisualEffectGraphs":true,"m_FxEnabled":true},"in2DMode":false,"pivot":{"x":0.026300787925720216,"y":-0.35891807079315188,"z":0.5774219632148743},"rotation":{"x":-0.21165692806243897,"y":0.786632239818573,"z":-0.3793974220752716,"w":-0.4387986361980438},"size":1.1368587017059327,"orthographic":false}